wbpHTMLpanel/__init__.py
wbpHTMLpanel-0.2.4.dist-info/LICENSE
wbpHTMLpanel-0.2.4.dist-info/METADATA
wbpHTMLpanel-0.2.4.dist-info/WHEEL
wbpHTMLpanel-0.2.4.dist-info/entry_points.txt
wbpHTMLpanel-0.2.4.dist-info/top_level.txt
wbpHTMLpanel-0.2.4.dist-info/RECORD
